LICENSE
setup.py
app/__init__.py
app/main.py
piops/__init__.py
piops/version.py
piops.egg-info/PKG-INFO
piops.egg-info/SOURCES.txt
piops.egg-info/dependency_links.txt
piops.egg-info/requires.txt
piops.egg-info/top_level.txt
piops/analysis/__init__.py
piops/analysis/distributions.py
piops/conformance/__init__.py
piops/discovery/__init__.py
piops/foundation/__init__.py
piops/operation/__init__.py
piops/prediction/__init__.py
piops/simulation/__init__.py